bsdl/__init__.py
bsdl/bsdl.py
bsdl/scrape.py
bsdl/test.py
bsdl-0.0.0.dist-info/LICENSE
bsdl-0.0.0.dist-info/METADATA
bsdl-0.0.0.dist-info/WHEEL
bsdl-0.0.0.dist-info/entry_points.txt
bsdl-0.0.0.dist-info/top_level.txt
bsdl-0.0.0.dist-info/RECORD
