Metadata-Version: 2.1
Name: bsdl
Version: 0.0.0
Summary: UNKNOWN
Home-page: UNKNOWN
Author: adithayyil
License: UNKNOWN
Platform: UNKNOWN
License-File: LICENSE
Requires-Dist: click
Requires-Dist: halo
Requires-Dist: mutagen
